{
  "positions": [
    {
      "id": "trade_1",
      "market_id": "540227",
      "market_question": "Will the New England Patriots win Super Bowl 2026?",
      "side": "YES",
      "entry_price": 0.3175,
      "amount": 2.0,
      "shares": 6.299212598425196,
      "current_price": 0.3175,
      "entry_time": "2026-02-05T18:19:20.948281",
      "opportunity_type": "near_certain",
      "status": "OPEN",
      "exit_price": null,
      "exit_time": null,
      "pnl": 0.0,
      "unrealized_pnl": 0.0,
      "hours_open": 0.10938168833333332,
      "extra_data": {}
    },
    {
      "id": "trade_2",
      "market_id": "1143975",
      "market_question": "Kings vs. Golden Knights",
      "side": "YES",
      "entry_price": 0.455,
      "amount": 2.0,
      "shares": 4.395604395604395,
      "current_price": 0.455,
      "entry_time": "2026-02-05T18:19:20.948281",
      "opportunity_type": "cross_platform_arb",
      "status": "OPEN",
      "exit_price": null,
      "exit_time": null,
      "pnl": 0.0,
      "unrealized_pnl": 0.0,
      "hours_open": 0.10938168833333332,
      "extra_data": {}
    },
    {
      "id": "trade_3",
      "market_id": "1308327",
      "market_question": "Another US government shutdown by February 14?",
      "side": "NO",
      "entry_price": 0.335,
      "amount": 2.0,
      "shares": 5.970149253731343,
      "current_price": 0.335,
      "entry_time": "2026-02-05T18:19:20.948281",
      "opportunity_type": "time_decay",
      "status": "OPEN",
      "exit_price": null,
      "exit_time": null,
      "pnl": 0.0,
      "unrealized_pnl": -0.0,
      "hours_open": 0.10938168833333332,
      "extra_data": {}
    },
    {
      "id": "trade_4",
      "market_id": "1303400",
      "market_question": "Will Bitcoin dip to $55,000 in February?",
      "side": "YES",
      "entry_price": 0.4095,
      "amount": 2.0,
      "shares": 4.884004884004884,
      "current_price": 0.489,
      "entry_time": "2026-02-05T18:19:20.948281",
      "opportunity_type": "momentum_long",
      "status": "OPEN",
      "exit_price": null,
      "exit_time": null,
      "pnl": 0.0,
      "unrealized_pnl": 0.3882783882783884,
      "hours_open": 0.10938168833333332,
      "extra_data": {}
    },
    {
      "id": "trade_5",
      "market_id": "540227",
      "market_question": "Will the New England Patriots win Super Bowl 2026?",
      "side": "YES",
      "entry_price": 0.3175,
      "amount": 2.0,
      "shares": 6.299212598425196,
      "current_price": 0.3175,
      "entry_time": "2026-02-05T18:22:35.818611",
      "opportunity_type": "near_certain",
      "status": "OPEN",
      "exit_price": null,
      "exit_time": null,
      "pnl": 0.0,
      "unrealized_pnl": 0.0,
      "hours_open": 0.055251041111111114,
      "extra_data": {}
    },
    {
      "id": "trade_6",
      "market_id": "1143975",
      "market_question": "Kings vs. Golden Knights",
      "side": "YES",
      "entry_price": 0.455,
      "amount": 2.0,
      "shares": 4.395604395604395,
      "current_price": 0.455,
      "entry_time": "2026-02-05T18:22:35.818611",
      "opportunity_type": "cross_platform_arb",
      "status": "OPEN",
      "exit_price": null,
      "exit_time": null,
      "pnl": 0.0,
      "unrealized_pnl": 0.0,
      "hours_open": 0.055251041111111114,
      "extra_data": {}
    },
    {
      "id": "trade_7",
      "market_id": "1308327",
      "market_question": "Another US government shutdown by February 14?",
      "side": "NO",
      "entry_price": 0.335,
      "amount": 2.0,
      "shares": 5.970149253731343,
      "current_price": 0.335,
      "entry_time": "2026-02-05T18:22:35.818611",
      "opportunity_type": "time_decay",
      "status": "OPEN",
      "exit_price": null,
      "exit_time": null,
      "pnl": 0.0,
      "unrealized_pnl": -0.0,
      "hours_open": 0.055251041111111114,
      "extra_data": {}
    },
    {
      "id": "trade_8",
      "market_id": "1303400",
      "market_question": "Will Bitcoin dip to $55,000 in February?",
      "side": "YES",
      "entry_price": 0.489,
      "amount": 2.0,
      "shares": 4.08997955010225,
      "current_price": 0.489,
      "entry_time": "2026-02-05T18:22:35.818611",
      "opportunity_type": "momentum_long",
      "status": "OPEN",
      "exit_price": null,
      "exit_time": null,
      "pnl": 0.0,
      "unrealized_pnl": 0.0,
      "hours_open": 0.055251041111111114,
      "extra_data": {}
    },
    {
      "id": "trade_9",
      "market_id": "1303403",
      "market_question": "Will Bitcoin dip to $50,000 in February?",
      "side": "YES",
      "entry_price": 0.2385,
      "amount": 2.0,
      "shares": 8.385744234800839,
      "current_price": 0.2385,
      "entry_time": "2026-02-05T18:22:35.818611",
      "opportunity_type": "momentum_long",
      "status": "OPEN",
      "exit_price": null,
      "exit_time": null,
      "pnl": 0.0,
      "unrealized_pnl": 0.0,
      "hours_open": 0.055251041111111114,
      "extra_data": {}
    },
    {
      "id": "trade_10",
      "market_id": "1303403",
      "market_question": "Will Bitcoin dip to $50,000 in February?",
      "side": "YES",
      "entry_price": 0.2385,
      "amount": 2.0,
      "shares": 8.385744234800839,
      "current_price": 0.2385,
      "entry_time": "2026-02-05T18:25:54.722359",
      "opportunity_type": "momentum_long",
      "status": "OPEN",
      "exit_price": null,
      "exit_time": null,
      "pnl": 0.0,
      "unrealized_pnl": 0.0,
      "hours_open": 0.0,
      "extra_data": {}
    }
  ],
  "closed_positions": [],
  "stats": {
    "total_scans": 3,
    "total_opportunities": 124,
    "total_trades": 10,
    "total_invested": 20.0,
    "realized_pnl": 0.0,
    "wins": 0,
    "losses": 0
  },
  "trade_counter": 10,
  "last_updated": "2026-02-05T18:25:54.722359"
}